{"elements":[{"type":"ellipse","version":112,"versionNonce":1794882032,"isDeleted":true,"id":"6KnLEulb2iIquF13Mf_td","fillStyle":"hachure","strokeWidth":1,"strokeStyle":"solid","roughness":1,"opacity":100,"angle":0,"x":607.9037017822266,"y":95.82034301757812,"strokeColor":"#000000","backgroundColor":"transparent","width":21.71002197265624,"height":22.365417480468743,"seed":550273808,"groupIds":[],"strokeSharpness":"sharp","boundElements":[],"updated":1651757060842,"link":null},{"type":"ellipse","version":609,"versionNonce":1544848474,"isDeleted":false,"id":"NjQTnnRSu8zLYwqnErSQe","fillStyle":"hachure","strokeWidth":1,"strokeStyle":"solid","roughness":1,"opacity":100,"angle":0,"x":842.0788636482946,"y":129.51385498046875,"strokeColor":"#000000","backgroundColor":"transparent","width":49.36615108414978,"height":49.43775030640327,"seed":1161385232,"groupIds":[],"strokeSharpness":"sharp","boundElements":[],"updated":1651757216561,"link":null},{"type":"ellipse","version":148,"versionNonce":1533334512,"isDeleted":true,"id":"0qQt_gEOoP0aEmfYCm9vI","fillStyle":"hachure","strokeWidth":1,"strokeStyle":"solid","roughness":1,"opacity":100,"angle":0,"x":599.5746612548828,"y":177.52169799804688,"strokeColor":"#000000","backgroundColor":"transparent","width":14.201416015625,"height":13.467864990234375,"seed":1678976272,"groupIds":[],"strokeSharpness":"sharp","boundElements":[],"updated":1651757043692,"link":null},{"type":"ellipse","version":140,"versionNonce":418816784,"isDeleted":true,"id":"3pdmuLOAkTNGALtlcM-e6","fillStyle":"hachure","strokeWidth":1,"strokeStyle":"solid","roughness":1,"opacity":100,"angle":0,"x":641.2152862548828,"y":178.12066650390625,"strokeColor":"#000000","backgroundColor":"transparent","width":15.1475830078125,"height":15.2734375,"seed":61584144,"groupIds":[],"strokeSharpness":"sharp","boundElements":[],"updated":1651757043692,"link":null},{"type":"ellipse","version":111,"versionNonce":293918192,"isDeleted":true,"id":"X2-LBfFFgxPVaAWZlHVCD","fillStyle":"hachure","strokeWidth":1,"strokeStyle":"solid","roughness":1,"opacity":100,"angle":0,"x":682.0747222900391,"y":179.02777099609375,"strokeColor":"#000000","backgroundColor":"transparent","width":16.7274169921875,"height":15.19964599609375,"seed":1181845776,"groupIds":[],"strokeSharpness":"sharp","boundElements":[],"updated":1651757043692,"link":null},{"type":"ellipse","version":818,"versionNonce":11011654,"isDeleted":false,"id":"1-THuVW_ykj-jwQ5gQ2yl","fillStyle":"hachure","strokeWidth":1,"strokeStyle":"solid","roughness":1,"opacity":100,"angle":0,"x":615.778819302652,"y":348.35384568392453,"strokeColor":"#000000","backgroundColor":"transparent","width":24.453014795358666,"height":24.48848073310445,"seed":264965104,"groupIds":[],"strokeSharpness":"sharp","boundElements":[],"updated":1651757216561,"link":null},{"type":"ellipse","version":832,"versionNonce":1115089178,"isDeleted":false,"id":"J88uvr-ZkJ_7CdugxGddn","fillStyle":"hachure","strokeWidth":1,"strokeStyle":"solid","roughness":1,"opacity":100,"angle":0,"x":761.1136636571166,"y":348.9384154293525,"strokeColor":"#000000","backgroundColor":"transparent","width":23.245274735051492,"height":22.044577910268462,"seed":1865411344,"groupIds":[],"strokeSharpness":"sharp","boundElements":[],"updated":1651757216561,"link":null},{"type":"ellipse","version":813,"versionNonce":1939557766,"isDeleted":false,"id":"cs2F3WUqUSYoF47ymsC-M","fillStyle":"hachure","strokeWidth":1,"strokeStyle":"solid","roughness":1,"opacity":100,"angle":0,"x":883.1290181262532,"y":352.54948227501677,"strokeColor":"#000000","backgroundColor":"transparent","width":24.793987317968337,"height":24.99998946904399,"seed":1281625584,"groupIds":[],"strokeSharpness":"sharp","boundElements":[],"updated":1651757216561,"link":null},{"type":"ellipse","version":840,"versionNonce":548320730,"isDeleted":false,"id":"adHzbX7FwB0XRpfKIzZWN","fillStyle":"hachure","strokeWidth":1,"strokeStyle":"solid","roughness":1,"opacity":100,"angle":0,"x":1041.8164310910045,"y":351.0527968886238,"strokeColor":"#000000","backgroundColor":"transparent","width":27.379903747862585,"height":24.879205472608284,"seed":639633680,"groupIds":[],"strokeSharpness":"sharp","boundElements":[],"updated":1651757216561,"link":null},{"type":"line","version":663,"versionNonce":253996230,"isDeleted":false,"id":"6p0tTPGkz44IX7ZtTN_Bc","fillStyle":"hachure","strokeWidth":1,"strokeStyle":"solid","roughness":1,"opacity":100,"angle":0,"x":861.0540265386812,"y":176.8683894492216,"strokeColor":"#000000","backgroundColor":"transparent","width":218.0964985890314,"height":168.89626153403387,"seed":469932304,"groupIds":[],"strokeSharpness":"round","boundElements":[],"updated":1651757216561,"link":null,"startBinding":null,"endBinding":null,"lastCommittedPoint":null,"startArrowhead":null,"endArrowhead":null,"points":[[0,0],[-218.0964985890314,168.89626153403387]]},{"type":"line","version":611,"versionNonce":667871898,"isDeleted":false,"id":"_UpYVpt9exRsXYmLehGj4","fillStyle":"hachure","strokeWidth":1,"strokeStyle":"solid","roughness":1,"opacity":100,"angle":0,"x":860.9241572227511,"y":182.7795814801282,"strokeColor":"#000000","backgroundColor":"transparent","width":77.50128071607041,"height":160.7924441880957,"seed":796968720,"groupIds":[],"strokeSharpness":"round","boundElements":[],"updated":1651757216561,"link":null,"startBinding":null,"endBinding":null,"lastCommittedPoint":null,"startArrowhead":null,"endArrowhead":null,"points":[[0,0],[-77.50128071607041,160.7924441880957]]},{"type":"line","version":571,"versionNonce":819864582,"isDeleted":false,"id":"INi2u7XNEvC55eAO-eMAi","fillStyle":"hachure","strokeWidth":1,"strokeStyle":"solid","roughness":1,"opacity":100,"angle":0,"x":869.1427987980094,"y":179.94928210503795,"strokeColor":"#000000","backgroundColor":"transparent","width":28.676824365827265,"height":164.3918393292255,"seed":1302889456,"groupIds":[],"strokeSharpness":"round","boundElements":[],"updated":1651757216561,"link":null,"startBinding":null,"endBinding":null,"lastCommittedPoint":null,"startArrowhead":null,"endArrowhead":null,"points":[[0,0],[28.676824365827265,164.3918393292255]]},{"type":"line","version":619,"versionNonce":1854572378,"isDeleted":false,"id":"2plWltUgbzO8YB1OamUcA","fillStyle":"hachure","strokeWidth":1,"strokeStyle":"solid","roughness":1,"opacity":100,"angle":0,"x":882.4081315903625,"y":183.3781260279264,"strokeColor":"#000000","backgroundColor":"transparent","width":161.05799476457608,"height":158.15435378200084,"seed":1145327088,"groupIds":[],"strokeSharpness":"round","boundElements":[],"updated":1651757216561,"link":null,"startBinding":null,"endBinding":null,"lastCommittedPoint":null,"startArrowhead":null,"endArrowhead":null,"points":[[0,0],[161.05799476457608,158.15435378200084]]},{"type":"ellipse","version":179,"versionNonce":220638192,"isDeleted":true,"id":"Yq88-Fsuw9pL8_JVT96tx","fillStyle":"hachure","strokeWidth":1,"strokeStyle":"solid","roughness":1,"opacity":100,"angle":0,"x":514.8133392333984,"y":582.0639874006181,"strokeColor":"#000000","backgroundColor":"transparent","width":14.93927001953125,"height":14.9609375,"seed":2084046096,"groupIds":[],"strokeSharpness":"sharp","boundElements":[],"updated":1651757102894,"link":null},{"type":"ellipse","version":330,"versionNonce":1054755600,"isDeleted":true,"id":"yoVG1Mf5v0MW6lvRmgXrm","fillStyle":"hachure","strokeWidth":1,"strokeStyle":"solid","roughness":1,"opacity":100,"angle":0,"x":481.04945373535156,"y":642.5877662072575,"strokeColor":"#000000","backgroundColor":"transparent","width":7.4000136287057545,"height":7.410746392124505,"seed":117609456,"groupIds":[],"strokeSharpness":"sharp","boundElements":[],"updated":1651757102894,"link":null},{"type":"ellipse","version":364,"versionNonce":1565240816,"isDeleted":true,"id":"gPH9zwnXZOUhxFUSy7fjM","fillStyle":"hachure","strokeWidth":1,"strokeStyle":"solid","roughness":1,"opacity":100,"angle":0,"x":506.16901790332395,"y":641.5601116681962,"strokeColor":"#000000","backgroundColor":"transparent","width":7.0345252428768,"height":6.671168293163408,"seed":1326768912,"groupIds":[],"strokeSharpness":"sharp","boundElements":[],"updated":1651757102894,"link":null},{"type":"ellipse","version":356,"versionNonce":822241552,"isDeleted":true,"id":"LQqgDSYwGW0xhW4PN2PBy","fillStyle":"hachure","strokeWidth":1,"strokeStyle":"solid","roughness":1,"opacity":100,"angle":0,"x":526.7952728746154,"y":641.8568045521677,"strokeColor":"#000000","backgroundColor":"transparent","width":7.503199323207718,"height":7.56554005044565,"seed":57316848,"groupIds":[],"strokeSharpness":"sharp","boundElements":[],"updated":1651757102894,"link":null},{"type":"ellipse","version":327,"versionNonce":629174256,"isDeleted":true,"id":"8l-ZYEgeqRT52Htg0-NnA","fillStyle":"hachure","strokeWidth":1,"strokeStyle":"solid","roughness":1,"opacity":100,"angle":0,"x":547.0345739332406,"y":642.3061294252086,"strokeColor":"#000000","backgroundColor":"transparent","width":8.285753825548412,"height":7.528988188549116,"seed":782631184,"groupIds":[],"strokeSharpness":"sharp","boundElements":[],"updated":1651757102894,"link":null},{"type":"line","version":78,"versionNonce":1156761360,"isDeleted":true,"id":"3v37ZyXoaLRUOjW3DpPNI","fillStyle":"hachure","strokeWidth":1,"strokeStyle":"solid","roughness":1,"opacity":100,"angle":0,"x":520.9374847412109,"y":596.4086529279618,"strokeColor":"#000000","backgroundColor":"transparent","width":33.0555419921875,"height":43.8194580078125,"seed":2005030896,"groupIds":[],"strokeSharpness":"round","boundElements":[],"updated":1651757102895,"link":null,"startBinding":null,"endBinding":null,"lastCommittedPoint":null,"startArrowhead":null,"endArrowhead":null,"points":[[0,0],[-33.0555419921875,43.8194580078125]]},{"type":"line","version":111,"versionNonce":1305276912,"isDeleted":true,"id":"Cqmd00NaNnDJ1NOywQEIp","fillStyle":"hachure","strokeWidth":1,"strokeStyle":"solid","roughness":1,"opacity":100,"angle":0,"x":520.5338592529297,"y":598.7567364240556,"strokeColor":"#000000","backgroundColor":"transparent","width":11.232666015625,"height":41.11114501953125,"seed":2053332752,"groupIds":[],"strokeSharpness":"round","boundElements":[],"updated":1651757102895,"link":null,"startBinding":null,"endBinding":null,"lastCommittedPoint":null,"startArrowhead":null,"endArrowhead":null,"points":[[0,0],[-11.232666015625,41.11114501953125]]},{"type":"line","version":102,"versionNonce":1999070480,"isDeleted":true,"id":"UdgkWNUelwe8Q_-KJ-uJw","fillStyle":"hachure","strokeWidth":1,"strokeStyle":"solid","roughness":1,"opacity":100,"angle":0,"x":523.0685882568359,"y":597.3895489240556,"strokeColor":"#000000","backgroundColor":"transparent","width":8.34197998046875,"height":42.76910400390625,"seed":1464982000,"groupIds":[],"strokeSharpness":"round","boundElements":[],"updated":1651757102895,"link":null,"startBinding":null,"endBinding":null,"lastCommittedPoint":null,"startArrowhead":null,"endArrowhead":null,"points":[[0,0],[8.34197998046875,42.76910400390625]]},{"type":"line","version":112,"versionNonce":2100900848,"isDeleted":true,"id":"1JFoKnoDazPb6hQg66_Fz","fillStyle":"hachure","strokeWidth":1,"strokeStyle":"solid","roughness":1,"opacity":100,"angle":0,"x":527.6041717529297,"y":599.1082989240556,"strokeColor":"#000000","backgroundColor":"transparent","width":25.4383544921875,"height":41.81427001953125,"seed":1657077008,"groupIds":[],"strokeSharpness":"round","boundElements":[],"updated":1651757102895,"link":null,"startBinding":null,"endBinding":null,"lastCommittedPoint":null,"startArrowhead":null,"endArrowhead":null,"points":[[0,0],[25.4383544921875,41.81427001953125]]},{"type":"ellipse","version":1075,"versionNonce":2059907910,"isDeleted":false,"id":"VKn1Z1uNnOuR56r_dBfXm","fillStyle":"hachure","strokeWidth":1,"strokeStyle":"solid","roughness":1,"opacity":100,"angle":0,"x":618.1074511907796,"y":350.94665552204833,"strokeColor":"#000000","backgroundColor":"transparent","width":24.690961999812245,"height":24.72677304922674,"seed":1394856720,"groupIds":[],"strokeSharpness":"sharp","boundElements":[],"updated":1651757216561,"link":null},{"type":"ellipse","version":1286,"versionNonce":1026853914,"isDeleted":false,"id":"tPWx25CW1XLGKnLGA80fp","fillStyle":"hachure","strokeWidth":1,"strokeStyle":"solid","roughness":1,"opacity":100,"angle":0,"x":504.92127659982316,"y":460.40161151583584,"strokeColor":"#000000","backgroundColor":"transparent","width":12.230413873341295,"height":12.248152508052275,"seed":1073915376,"groupIds":[],"strokeSharpness":"sharp","boundElements":[],"updated":1651757216561,"link":null},{"type":"ellipse","version":1296,"versionNonce":1195203206,"isDeleted":false,"id":"wSR9569Ixp3zn5hqRwdYQ","fillStyle":"hachure","strokeWidth":1,"strokeStyle":"solid","roughness":1,"opacity":100,"angle":0,"x":577.6119166517053,"y":460.6939897761148,"strokeColor":"#000000","backgroundColor":"transparent","width":11.626350901450623,"height":11.02581067250959,"seed":861335824,"groupIds":[],"strokeSharpness":"sharp","boundElements":[],"updated":1651757216561,"link":null},{"type":"ellipse","version":1279,"versionNonce":1505753306,"isDeleted":false,"id":"pLqO-l1UMePAC2z59RvT6","fillStyle":"hachure","strokeWidth":1,"strokeStyle":"solid","roughness":1,"opacity":100,"angle":0,"x":638.6390863708039,"y":462.5001000826094,"strokeColor":"#000000","backgroundColor":"transparent","width":12.400954606492329,"height":12.503988591771385,"seed":110651376,"groupIds":[],"strokeSharpness":"sharp","boundElements":[],"updated":1651757216561,"link":null},{"type":"ellipse","version":1308,"versionNonce":486283718,"isDeleted":false,"id":"a3SfViOyQo6jAOvcmykm_","fillStyle":"hachure","strokeWidth":1,"strokeStyle":"solid","roughness":1,"opacity":100,"angle":0,"x":718.0081438588438,"y":461.7515182874005,"strokeColor":"#000000","backgroundColor":"transparent","width":13.694325932856664,"height":12.443577297783833,"seed":460738320,"groupIds":[],"strokeSharpness":"sharp","boundElements":[],"updated":1651757216561,"link":null},{"type":"line","version":1150,"versionNonce":1405078938,"isDeleted":false,"id":"RiAHznT1AINInzFi5FRDm","fillStyle":"hachure","strokeWidth":1,"strokeStyle":"solid","roughness":1,"opacity":100,"angle":0,"x":629.0359492730192,"y":374.60894679408955,"strokeColor":"#000000","backgroundColor":"transparent","width":109.08309116047087,"height":84.4751126807237,"seed":958786032,"groupIds":[],"strokeSharpness":"round","boundElements":[],"updated":1651757216561,"link":null,"startBinding":null,"endBinding":null,"lastCommittedPoint":null,"startArrowhead":null,"endArrowhead":null,"points":[[0,0],[-109.08309116047087,84.4751126807237]]},{"type":"line","version":1098,"versionNonce":589361414,"isDeleted":false,"id":"EwVLPvGLdwTXXnJc4JDLz","fillStyle":"hachure","strokeWidth":1,"strokeStyle":"solid","roughness":1,"opacity":100,"angle":0,"x":629.0821171274679,"y":378.0151321288705,"strokeColor":"#000000","backgroundColor":"transparent","width":38.76302152532367,"height":80.42190938762316,"seed":1140452624,"groupIds":[],"strokeSharpness":"round","boundElements":[],"updated":1651757216561,"link":null,"startBinding":null,"endBinding":null,"lastCommittedPoint":null,"startArrowhead":null,"endArrowhead":null,"points":[[0,0],[-38.76302152532367,80.42190938762316]]},{"type":"line","version":1046,"versionNonce":1348930138,"isDeleted":false,"id":"b6g90_kENqUAp5FrMrg29","fillStyle":"hachure","strokeWidth":1,"strokeStyle":"solid","roughness":1,"opacity":100,"angle":0,"x":633.2303635082424,"y":376.34763968148195,"strokeColor":"#000000","backgroundColor":"transparent","width":14.342993430558765,"height":82.22218197724531,"seed":45296624,"groupIds":[],"strokeSharpness":"round","boundElements":[],"updated":1651757216561,"link":null,"startBinding":null,"endBinding":null,"lastCommittedPoint":null,"startArrowhead":null,"endArrowhead":null,"points":[[0,0],[14.342993430558765,82.22218197724531]]},{"type":"line","version":1106,"versionNonce":355000390,"isDeleted":false,"id":"VmJNuFhEYpnPSZHJbbKAD","fillStyle":"hachure","strokeWidth":1,"strokeStyle":"solid","roughness":1,"opacity":100,"angle":0,"x":639.9862842966927,"y":378.3922248722598,"strokeColor":"#000000","backgroundColor":"transparent","width":80.55472709872502,"height":79.10244273813845,"seed":374983440,"groupIds":[],"strokeSharpness":"round","boundElements":[],"updated":1651757216561,"link":null,"startBinding":null,"endBinding":null,"lastCommittedPoint":null,"startArrowhead":null,"endArrowhead":null,"points":[[0,0],[80.55472709872502,79.10244273813845]]},{"type":"ellipse","version":868,"versionNonce":1451798298,"isDeleted":false,"id":"CE0W_0Fjw15aNb7lsRa7F","fillStyle":"hachure","strokeWidth":1,"strokeStyle":"solid","roughness":1,"opacity":100,"angle":0,"x":501.9899922256507,"y":460.3316707239668,"strokeColor":"#000000","backgroundColor":"transparent","width":15.32716272885148,"height":15.349392797565333,"seed":1609013744,"groupIds":[],"strokeSharpness":"sharp","boundElements":[],"updated":1651757216561,"link":null},{"type":"ellipse","version":1077,"versionNonce":921757574,"isDeleted":false,"id":"A70OfDT-aliLjKHNPHxlJ","fillStyle":"hachure","strokeWidth":1,"strokeStyle":"solid","roughness":1,"opacity":100,"angle":0,"x":431.7285371788625,"y":528.276934339407,"strokeColor":"#000000","backgroundColor":"transparent","width":7.592152289543454,"height":7.603163725258461,"seed":661339408,"groupIds":[],"strokeSharpness":"sharp","boundElements":[],"updated":1651757216561,"link":null},{"type":"ellipse","version":1089,"versionNonce":446151642,"isDeleted":false,"id":"gWL1VijNRcJdZSOrVuLgL","fillStyle":"hachure","strokeWidth":1,"strokeStyle":"solid","roughness":1,"opacity":100,"angle":0,"x":476.85198230619403,"y":528.4584310819679,"strokeColor":"#000000","backgroundColor":"transparent","width":7.217174130785903,"height":6.844382750106979,"seed":1170136048,"groupIds":[],"strokeSharpness":"sharp","boundElements":[],"updated":1651757216561,"link":null},{"type":"ellipse","version":1070,"versionNonce":1219888838,"isDeleted":false,"id":"czDWfnGK16IuY685uH_hH","fillStyle":"hachure","strokeWidth":1,"strokeStyle":"solid","roughness":1,"opacity":100,"angle":0,"x":514.7352110428053,"y":529.579592200523,"strokeColor":"#000000","backgroundColor":"transparent","width":7.698017163051544,"height":7.761976544585017,"seed":522263312,"groupIds":[],"strokeSharpness":"sharp","boundElements":[],"updated":1651757216561,"link":null},{"type":"ellipse","version":1097,"versionNonce":1252470938,"isDeleted":false,"id":"hHoTLEeEGQxLeHD7upsUd","fillStyle":"hachure","strokeWidth":1,"strokeStyle":"solid","roughness":1,"opacity":100,"angle":0,"x":564.0043508909794,"y":529.1149025302249,"strokeColor":"#000000","backgroundColor":"transparent","width":8.500890408256303,"height":7.724475626896388,"seed":861789680,"groupIds":[],"strokeSharpness":"sharp","boundElements":[],"updated":1651757216561,"link":null},{"type":"line","version":925,"versionNonce":2064989702,"isDeleted":false,"id":"us11eMDV_41JitxBnpEf0","fillStyle":"hachure","strokeWidth":1,"strokeStyle":"solid","roughness":1,"opacity":100,"angle":0,"x":508.8423043194193,"y":475.3236039966348,"strokeColor":"#000000","backgroundColor":"transparent","width":67.71442478407239,"height":52.43877490902799,"seed":543897872,"groupIds":[],"strokeSharpness":"round","boundElements":[],"updated":1651757216561,"link":null,"startBinding":null,"endBinding":null,"lastCommittedPoint":null,"startArrowhead":null,"endArrowhead":null,"points":[[0,0],[-67.71442478407239,52.43877490902799]]},{"type":"line","version":868,"versionNonce":1516899674,"isDeleted":false,"id":"pxUkzHRYCEY2s1aCJYYM_","fillStyle":"hachure","strokeWidth":1,"strokeStyle":"solid","roughness":1,"opacity":100,"angle":0,"x":508.00945963271016,"y":477.32717522971666,"strokeColor":"#000000","backgroundColor":"transparent","width":24.062535059797423,"height":49.922708242733535,"seed":1506582512,"groupIds":[],"strokeSharpness":"round","boundElements":[],"updated":1651757216561,"link":null,"startBinding":null,"endBinding":null,"lastCommittedPoint":null,"startArrowhead":null,"endArrowhead":null,"points":[[0,0],[-24.062535059797423,49.922708242733535]]},{"type":"line","version":834,"versionNonce":1661701446,"isDeleted":false,"id":"PgCkF-27UQGZUTKUiMrFA","fillStyle":"hachure","strokeWidth":1,"strokeStyle":"solid","roughness":1,"opacity":100,"angle":0,"x":512.6866427868797,"y":475.79253768113927,"strokeColor":"#000000","backgroundColor":"transparent","width":8.903557274548222,"height":51.040245539888694,"seed":1858180880,"groupIds":[],"strokeSharpness":"round","boundElements":[],"updated":1651757216561,"link":null,"startBinding":null,"endBinding":null,"lastCommittedPoint":null,"startArrowhead":null,"endArrowhead":null,"points":[[0,0],[8.903557274548222,51.040245539888694]]},{"type":"line","version":876,"versionNonce":1328763418,"isDeleted":false,"id":"K_sLthQejz12_IOFgTwEu","fillStyle":"hachure","strokeWidth":1,"strokeStyle":"solid","roughness":1,"opacity":100,"angle":0,"x":514.6332973587362,"y":477.60194959322155,"strokeColor":"#000000","backgroundColor":"transparent","width":50.00515617130544,"height":49.10363606352488,"seed":152248816,"groupIds":[],"strokeSharpness":"round","boundElements":[],"updated":1651757216561,"link":null,"startBinding":null,"endBinding":null,"lastCommittedPoint":null,"startArrowhead":null,"endArrowhead":null,"points":[[0,0],[50.00515617130544,49.10363606352488]]},{"type":"ellipse","version":877,"versionNonce":1844835462,"isDeleted":false,"id":"n8iGOsNLuzTwvk5wY9dxO","fillStyle":"hachure","strokeWidth":1,"strokeStyle":"solid","roughness":1,"opacity":100,"angle":0,"x":428.9304782569984,"y":527.8850024385503,"strokeColor":"#000000","backgroundColor":"transparent","width":11.935262197504603,"height":11.952572752854083,"seed":620967920,"groupIds":[],"strokeSharpness":"sharp","boundElements":[],"updated":1651757216561,"link":null},{"type":"ellipse","version":1088,"versionNonce":200670938,"isDeleted":false,"id":"S65Jk0-sIfYxK2UOF3tsZ","fillStyle":"hachure","strokeWidth":1,"strokeStyle":"solid","roughness":1,"opacity":100,"angle":0,"x":374.21788055076564,"y":580.793981789461,"strokeColor":"#000000","backgroundColor":"transparent","width":5.912009275435932,"height":5.9205838808442985,"seed":165707536,"groupIds":[],"strokeSharpness":"sharp","boundElements":[],"updated":1651757216561,"link":null},{"type":"ellipse","version":1098,"versionNonce":1435595718,"isDeleted":false,"id":"t3MXfZfUdAj4lExEDftwR","fillStyle":"hachure","strokeWidth":1,"strokeStyle":"solid","roughness":1,"opacity":100,"angle":0,"x":409.35550898056243,"y":580.9353133097692,"strokeColor":"#000000","backgroundColor":"transparent","width":5.620013769008363,"height":5.329721106753442,"seed":1639365104,"groupIds":[],"strokeSharpness":"sharp","boundElements":[],"updated":1651757216561,"link":null},{"type":"ellipse","version":1079,"versionNonce":491066266,"isDeleted":false,"id":"GLJxk9sYlTDBERBduzMNK","fillStyle":"hachure","strokeWidth":1,"strokeStyle":"solid","roughness":1,"opacity":100,"angle":0,"x":438.85518063266636,"y":581.8083615152532,"strokeColor":"#000000","backgroundColor":"transparent","width":5.994446256446539,"height":6.044251429269245,"seed":1167990032,"groupIds":[],"strokeSharpness":"sharp","boundElements":[],"updated":1651757216561,"link":null},{"type":"ellipse","version":1108,"versionNonce":335219462,"isDeleted":false,"id":"QolF5_gCgbqrepLE05T58","fillStyle":"hachure","strokeWidth":1,"strokeStyle":"solid","roughness":1,"opacity":100,"angle":0,"x":477.22106169861394,"y":581.4465076513904,"strokeColor":"#000000","backgroundColor":"transparent","width":6.6196436828979675,"height":6.015049463244688,"seed":11140080,"groupIds":[],"strokeSharpness":"sharp","boundElements":[],"updated":1651757216561,"link":null},{"type":"line","version":936,"versionNonce":89362522,"isDeleted":false,"id":"EL8p2jmNE9ilKLfU5Xwzu","fillStyle":"hachure","strokeWidth":1,"strokeStyle":"solid","roughness":1,"opacity":100,"angle":0,"x":435.00987529282327,"y":539.646355958404,"strokeColor":"#000000","backgroundColor":"transparent","width":52.72922514418086,"height":40.83407600788703,"seed":871889680,"groupIds":[],"strokeSharpness":"round","boundElements":[],"updated":1651757216561,"link":null,"startBinding":null,"endBinding":null,"lastCommittedPoint":null,"startArrowhead":null,"endArrowhead":null,"points":[[0,0],[-52.72922514418086,40.83407600788703]]},{"type":"line","version":884,"versionNonce":1471134278,"isDeleted":false,"id":"bqJDWV9RlHfabQHX02nyr","fillStyle":"hachure","strokeWidth":1,"strokeStyle":"solid","roughness":1,"opacity":100,"angle":0,"x":435.36696850260967,"y":541.3199114404081,"strokeColor":"#000000","backgroundColor":"transparent","width":18.737496962482478,"height":38.87481479954232,"seed":602209776,"groupIds":[],"strokeSharpness":"round","boundElements":[],"updated":1651757216561,"link":null,"startBinding":null,"endBinding":null,"lastCommittedPoint":null,"startArrowhead":null,"endArrowhead":null,"points":[[0,0],[-18.737496962482478,38.87481479954232]]},{"type":"line","version":846,"versionNonce":133461274,"isDeleted":false,"id":"5H4mDTQqaqL2o6K2vHCfz","fillStyle":"hachure","strokeWidth":1,"strokeStyle":"solid","roughness":1,"opacity":100,"angle":0,"x":435.9734738983849,"y":540.4795224192835,"strokeColor":"#000000","backgroundColor":"transparent","width":6.933200386931313,"height":39.745041135166026,"seed":929437968,"groupIds":[],"strokeSharpness":"round","boundElements":[],"updated":1651757216561,"link":null,"startBinding":null,"endBinding":null,"lastCommittedPoint":null,"startArrowhead":null,"endArrowhead":null,"points":[[0,0],[6.933200386931313,39.745041135166026]]},{"type":"line","version":890,"versionNonce":2005696902,"isDeleted":false,"id":"mungehpZbZlCS1Js2auBy","fillStyle":"hachure","strokeWidth":1,"strokeStyle":"solid","roughness":1,"opacity":100,"angle":0,"x":440.4158829939561,"y":542.0238499585206,"strokeColor":"#000000","backgroundColor":"transparent","width":38.93901700464416,"height":38.23700326256851,"seed":1819262960,"groupIds":[],"strokeSharpness":"round","boundElements":[],"updated":1651757216561,"link":null,"startBinding":null,"endBinding":null,"lastCommittedPoint":null,"startArrowhead":null,"endArrowhead":null,"points":[[0,0],[38.93901700464416,38.23700326256851]]},{"type":"ellipse","version":1017,"versionNonce":1989853658,"isDeleted":false,"id":"cojmmnMSNEur1Np25Lhk8","fillStyle":"hachure","strokeWidth":1,"strokeStyle":"solid","roughness":1,"opacity":100,"angle":0,"x":373.3211677308586,"y":581.6890185943381,"strokeColor":"#000000","backgroundColor":"transparent","width":7.5399795275523775,"height":7.550915293418729,"seed":271552784,"groupIds":[],"strokeSharpness":"sharp","boundElements":[],"updated":1651757216561,"link":null},{"type":"ellipse","version":1226,"versionNonce":1724801222,"isDeleted":false,"id":"wohuHRcxYhVrJsyAiKEMJ","fillStyle":"hachure","strokeWidth":1,"strokeStyle":"solid","roughness":1,"opacity":100,"angle":0,"x":338.757045068312,"y":615.1137238524237,"strokeColor":"#000000","backgroundColor":"transparent","width":3.7348512471562265,"height":3.7402681662122146,"seed":2031732720,"groupIds":[],"strokeSharpness":"sharp","boundElements":[],"updated":1651757216561,"link":null},{"type":"ellipse","version":1238,"versionNonce":2086237850,"isDeleted":false,"id":"xJsYzuyB_C7d92p3JPdy6","fillStyle":"hachure","strokeWidth":1,"strokeStyle":"solid","roughness":1,"opacity":100,"angle":0,"x":360.95488158193314,"y":615.2030085913814,"strokeColor":"#000000","backgroundColor":"transparent","width":3.5503860796409716,"height":3.366996666473457,"seed":339406608,"groupIds":[],"strokeSharpness":"sharp","boundElements":[],"updated":1651757216561,"link":null},{"type":"ellipse","version":1221,"versionNonce":689068038,"isDeleted":false,"id":"cVczvZv2TMOci0BqFngtA","fillStyle":"hachure","strokeWidth":1,"strokeStyle":"solid","roughness":1,"opacity":100,"angle":0,"x":379.5909967041373,"y":615.7545478443116,"strokeColor":"#000000","backgroundColor":"transparent","width":3.7869299647283587,"height":3.818393872033887,"seed":343624176,"groupIds":[],"strokeSharpness":"sharp","boundElements":[],"updated":1651757216561,"link":null},{"type":"ellipse","version":1250,"versionNonce":1776522074,"isDeleted":false,"id":"5HgUN-6nVL2SP4ic1PBnJ","fillStyle":"hachure","strokeWidth":1,"strokeStyle":"solid","roughness":1,"opacity":100,"angle":0,"x":403.82824872313495,"y":615.5259503757053,"strokeColor":"#000000","backgroundColor":"transparent","width":4.181892029081492,"height":3.7999458293896686,"seed":2066386192,"groupIds":[],"strokeSharpness":"sharp","boundElements":[],"updated":1651757216561,"link":null},{"type":"line","version":1073,"versionNonce":1180002118,"isDeleted":false,"id":"U6PLUBH1AN8E92lRG7qxw","fillStyle":"hachure","strokeWidth":1,"strokeStyle":"solid","roughness":1,"opacity":100,"angle":0,"x":378.6237278251634,"y":588.5019978641576,"strokeColor":"#000000","backgroundColor":"transparent","width":33.311147380905275,"height":25.7965088685155,"seed":207391728,"groupIds":[],"strokeSharpness":"round","boundElements":[],"updated":1651757216561,"link":null,"startBinding":null,"endBinding":null,"lastCommittedPoint":null,"startArrowhead":null,"endArrowhead":null,"points":[[0,0],[-33.311147380905275,25.7965088685155]]},{"type":"line","version":1019,"versionNonce":25958426,"isDeleted":false,"id":"Inhtagg3GEhWGgzRH7-hq","fillStyle":"hachure","strokeWidth":1,"strokeStyle":"solid","roughness":1,"opacity":100,"angle":0,"x":378.45263892036587,"y":590.9145753374468,"strokeColor":"#000000","backgroundColor":"transparent","width":11.837221600731242,"height":24.55876568737831,"seed":1584818960,"groupIds":[],"strokeSharpness":"round","boundElements":[],"updated":1651757216561,"link":null,"startBinding":null,"endBinding":null,"lastCommittedPoint":null,"startArrowhead":null,"endArrowhead":null,"points":[[0,0],[-11.837221600731242,24.55876568737831]]},{"type":"line","version":981,"versionNonce":1056214662,"isDeleted":false,"id":"nwT-k6cN35c4DfWd-ZVcp","fillStyle":"hachure","strokeWidth":1,"strokeStyle":"solid","roughness":1,"opacity":100,"angle":0,"x":379.7655313001657,"y":590.2031432340265,"strokeColor":"#000000","backgroundColor":"transparent","width":4.379978262129016,"height":25.108522252953467,"seed":986025456,"groupIds":[],"strokeSharpness":"round","boundElements":[],"updated":1651757216561,"link":null,"startBinding":null,"endBinding":null,"lastCommittedPoint":null,"startArrowhead":null,"endArrowhead":null,"points":[[0,0],[4.379978262129016,25.108522252953467]]},{"type":"line","version":1029,"versionNonce":1128662234,"isDeleted":false,"id":"gTwhzBR4QsC7yJroL3jZv","fillStyle":"hachure","strokeWidth":1,"strokeStyle":"solid","roughness":1,"opacity":100,"angle":0,"x":381.79346677119264,"y":591.1348773407794,"strokeColor":"#000000","backgroundColor":"transparent","width":24.59932477222121,"height":24.15583478802821,"seed":1754695952,"groupIds":[],"strokeSharpness":"round","boundElements":[],"updated":1651757216561,"link":null,"startBinding":null,"endBinding":null,"lastCommittedPoint":null,"startArrowhead":null,"endArrowhead":null,"points":[[0,0],[24.59932477222121,24.15583478802821]]},{"type":"ellipse","version":1020,"versionNonce":2142031302,"isDeleted":false,"id":"dd9MRZuk6WIdeDJeXm6Lf","fillStyle":"hachure","strokeWidth":1,"strokeStyle":"solid","roughness":1,"opacity":100,"angle":0,"x":337.74347295648874,"y":614.5966987793233,"strokeColor":"#000000","backgroundColor":"transparent","width":4.272147422726922,"height":4.278343620447458,"seed":498020848,"groupIds":[],"strokeSharpness":"sharp","boundElements":[],"updated":1651757216561,"link":null},{"type":"ellipse","version":1229,"versionNonce":950294938,"isDeleted":false,"id":"jqNHzljeMiGqIKYgYRyVV","fillStyle":"hachure","strokeWidth":1,"strokeStyle":"solid","roughness":1,"opacity":100,"angle":0,"x":318.1594638737019,"y":633.5351147129394,"strokeColor":"#000000","backgroundColor":"transparent","width":2.116164251043598,"height":2.119233473804693,"seed":1032398096,"groupIds":[],"strokeSharpness":"sharp","boundElements":[],"updated":1651757216561,"link":null},{"type":"ellipse","version":1241,"versionNonce":1436230918,"isDeleted":false,"id":"Ngq7IQj458-m-AgW7nVVp","fillStyle":"hachure","strokeWidth":1,"strokeStyle":"solid","roughness":1,"opacity":100,"angle":0,"x":330.7367433882229,"y":633.5857033870907,"strokeColor":"#000000","backgroundColor":"transparent","width":2.0116464089057673,"height":1.9077380884711992,"seed":382956528,"groupIds":[],"strokeSharpness":"sharp","boundElements":[],"updated":1651757216561,"link":null},{"type":"ellipse","version":1220,"versionNonce":1088034394,"isDeleted":false,"id":"SLl6m_NQ4b1iHRAexHstB","fillStyle":"hachure","strokeWidth":1,"strokeStyle":"solid","roughness":1,"opacity":100,"angle":0,"x":341.2959539136662,"y":633.8982051636974,"strokeColor":"#000000","backgroundColor":"transparent","width":2.14567201803974,"height":2.163499447147871,"seed":155321104,"groupIds":[],"strokeSharpness":"sharp","boundElements":[],"updated":1651757216561,"link":null},{"type":"ellipse","version":1251,"versionNonce":1648137286,"isDeleted":false,"id":"d5x10XATwkyhrpUy6WY8p","fillStyle":"hachure","strokeWidth":1,"strokeStyle":"solid","roughness":1,"opacity":100,"angle":0,"x":355.028764907193,"y":633.7686819888954,"strokeColor":"#000000","backgroundColor":"transparent","width":2.3694572629645143,"height":2.1530467983642976,"seed":639596016,"groupIds":[],"strokeSharpness":"sharp","boundElements":[],"updated":1651757216561,"link":null},{"type":"line","version":1075,"versionNonce":1555708698,"isDeleted":false,"id":"nxz4XRxsjYeeDmm5KIgGf","fillStyle":"hachure","strokeWidth":1,"strokeStyle":"solid","roughness":1,"opacity":100,"angle":0,"x":341.0136714217296,"y":618.7456423983775,"strokeColor":"#000000","backgroundColor":"transparent","width":18.874074115372025,"height":14.616284895107118,"seed":1714364688,"groupIds":[],"strokeSharpness":"round","boundElements":[],"updated":1651757216561,"link":null,"startBinding":null,"endBinding":null,"lastCommittedPoint":null,"startArrowhead":null,"endArrowhead":null,"points":[[0,0],[-18.874074115372025,14.616284895107118]]},{"type":"line","version":1021,"versionNonce":258874246,"isDeleted":false,"id":"utavwUWSNy0Sl7KoSU4jU","fillStyle":"hachure","strokeWidth":1,"strokeStyle":"solid","roughness":1,"opacity":100,"angle":0,"x":338.9852797693331,"y":620.1782285584558,"strokeColor":"#000000","backgroundColor":"transparent","width":6.706961944527664,"height":13.914980425781877,"seed":815478768,"groupIds":[],"strokeSharpness":"round","boundElements":[],"updated":1651757216561,"link":null,"startBinding":null,"endBinding":null,"lastCommittedPoint":null,"startArrowhead":null,"endArrowhead":null,"points":[[0,0],[-6.706961944527664,13.914980425781877]]},{"type":"line","version":987,"versionNonce":2058864602,"isDeleted":false,"id":"gdw1LHdbmofhmEpS2UNXZ","fillStyle":"hachure","strokeWidth":1,"strokeStyle":"solid","roughness":1,"opacity":100,"angle":0,"x":341.62874644732545,"y":618.5961219475668,"strokeColor":"#000000","backgroundColor":"transparent","width":2.481692791840864,"height":14.226472132910148,"seed":600342288,"groupIds":[],"strokeSharpness":"round","boundElements":[],"updated":1651757216561,"link":null,"startBinding":null,"endBinding":null,"lastCommittedPoint":null,"startArrowhead":null,"endArrowhead":null,"points":[[0,0],[2.481692791840864,14.226472132910148]]},{"type":"line","version":1031,"versionNonce":57457350,"isDeleted":false,"id":"p02OpK7Csiw1trv-chrqy","fillStyle":"hachure","strokeWidth":1,"strokeStyle":"solid","roughness":1,"opacity":100,"angle":0,"x":341.1327816245131,"y":620.4452310538868,"strokeColor":"#000000","backgroundColor":"transparent","width":13.93796117647846,"height":13.68668004420854,"seed":978237936,"groupIds":[],"strokeSharpness":"round","boundElements":[],"updated":1651757216561,"link":null,"startBinding":null,"endBinding":null,"lastCommittedPoint":null,"startArrowhead":null,"endArrowhead":null,"points":[[0,0],[13.93796117647846,13.68668004420854]]}]}